singbox2proxy/__init__.py
singbox2proxy/__main__.py
singbox2proxy/base.py
singbox2proxy/cli.py
tests/__init__.py
tests/core_test.py
tests/proxy_test.py
tests/route_test.py
singbox2proxy-0.2.6.dist-info/METADATA
singbox2proxy-0.2.6.dist-info/WHEEL
singbox2proxy-0.2.6.dist-info/entry_points.txt
singbox2proxy-0.2.6.dist-info/top_level.txt
singbox2proxy-0.2.6.dist-info/RECORD
