Metadata-Version: 2.4
Name: singbox2proxy
Version: 0.2.6
Summary: 🐳 Use sing-box (v2ray) proxies (VLESS + REALITY, VMess, Trojan, Shadowsocks, Hysteria, Hysteria2, TUIC, WireGuard, SSH) directly in your http clients, with chaining support and easy CLI
Author-email: nichind <nichind@proton.me>
License: MIT
Project-URL: Homepage, https://github.com/nichind/singbox2proxy
Project-URL: Issues, https://github.com/nichind/singbox2proxy/issues
Keywords: sing-box,hysteria2,v2ray,v2core,v2ray-core,proxy,vless,vmess,shadowsocks,trojan,python,cli
Classifier: Programming Language :: Python :: 3.9
Classifier: License :: OSI Approved :: MIT License
Classifier: Operating System :: OS Independent
Requires-Python: >=3.9
